README.rst
setup.py
bin/zotcite
bin/zrst2html
bin/zrst2odt
bin/zrst2pdf
bin/zrst2pseudoxml
bin/zrst2rst
bin/zupdatekeymap
test/test_jsonencoder.py
test/test_xcite.py
xciterst/__init__.py
xciterst/citations.py
xciterst/directives.py
xciterst/parser.py
xciterst/roles.py
xciterst/sphinx.py
xciterst/spidermonkey.py
xciterst/util.py
zot4rst/__init__.py
zot4rst/jsonencoder.py
zot4rst/pelican_plugin.py
zot4rst/sphinx.py
zot4rst.egg-info/PKG-INFO
zot4rst.egg-info/SOURCES.txt
zot4rst.egg-info/dependency_links.txt
zot4rst.egg-info/requires.txt
zot4rst.egg-info/top_level.txt