Metadata-Version: 1.0
Name: zot4rst
Version: 0.3.0
Summary: Zotero for reStructuredText
Home-page: http://bitbucket.org/egh/zot4rst/
Author: Erik Hetzner
Author-email: egh@e6h.org
License: UNKNOWN
Platform: UNKNOWN
